bench_logging_handler/__init__.py
bench_logging_handler/core/__init__.py
bench_logging_handler/core/builder.py
bench_logging_handler/core/enrichers.py
bench_logging_handler/core/handler.py
bench_logging_handler/core/schema.py
bench_logging_handler/core/formatters/__init__.py
bench_logging_handler/core/formatters/box_formatter.py
bench_logging_handler/core/formatters/json_formatter.py
bench_logging_handler/core/formatters/line_formatter.py
bench_logging_handler/extensions/base.py
bench_logging_handler/extensions/benchlogger.py
bench_logging_handler/storage/__init__.py
bench_logging_handler/storage/base.py
bench_logging_handler/storage/console_sink.py
bench_logging_handler/storage/file_sink.py
bench_logging_handler/webapp/__init__.py
bench_logging_handler/webapp/dashboard_generator.py
bench_logging_handler-0.1.0.dist-info/licenses/LICENSE
bench_logging_handler-0.1.0.dist-info/METADATA
bench_logging_handler-0.1.0.dist-info/WHEEL
bench_logging_handler-0.1.0.dist-info/top_level.txt
bench_logging_handler-0.1.0.dist-info/RECORD
