Metadata-Version: 2.4
Name: bench-logging-handler
Version: 0.1.0
Summary: A benchmarking logging handler that provides structured logging, performance measurement, and automatic stack traces
Author-email: KeonHo Park <imguno0629@gmail.com>
License: MIT License
Project-URL: Repository, https://github.com/imguno/bench-logging-handler
Project-URL: Issues, https://github.com/imguno/bench-logging-handler/issues
Project-URL: Documentation, https://github.com/imguno/bench-logging-handler#readme
Keywords: logging,structured,benchmark,monitoring
Classifier: Development Status :: 4 - Beta
Classifier: Intended Audience :: Developers
Classifier: License :: OSI Approved :: MIT License
Classifier: Operating System :: OS Independent
Classifier: Programming Language :: Python :: 3
Classifier: Programming Language :: Python :: 3.8
Classifier: Programming Language :: Python :: 3.9
Classifier: Programming Language :: Python :: 3.10
Classifier: Programming Language :: Python :: 3.11
Classifier: Programming Language :: Python :: 3.12
Classifier: Topic :: Software Development :: Libraries :: Python Modules
Classifier: Topic :: System :: Logging
Classifier: Topic :: System :: Monitoring
Requires-Python: >=3.8
License-File: LICENSE
Requires-Dist: psutil>=5.8.0
Dynamic: license-file
